byted_jeddak_io/__init__.py
byted_jeddak_io-0.0.1.dist-info/METADATA
byted_jeddak_io-0.0.1.dist-info/WHEEL
byted_jeddak_io-0.0.1.dist-info/top_level.txt
byted_jeddak_io-0.0.1.dist-info/RECORD
