Metadata-Version: 2.1
Name: byted-jeddak-io
Version: 0.0.1
Summary: A simple package named byted_jeddak_io
Home-page: https://github.com/artifact/byted_jeddak_io.git
Author: artifact
Author-email: artifact@example.com
License: UNKNOWN
Platform: UNKNOWN
Classifier: Programming Language :: Python :: 3
Classifier: License :: OSI Approved :: MIT License
Classifier: Operating System :: OS Independent
